mast_aladin_lite/__init__.py
mast_aladin_lite/app.py
mast_aladin_lite/tests/__init__.py
mast_aladin_lite-0.0.1.dist-info/LICENSE
mast_aladin_lite-0.0.1.dist-info/METADATA
mast_aladin_lite-0.0.1.dist-info/WHEEL
mast_aladin_lite-0.0.1.dist-info/top_level.txt
mast_aladin_lite-0.0.1.dist-info/RECORD
