Metadata-Version: 2.2
Name: mast-aladin-lite
Version: 0.0.1
Summary: Visualize MAST data products in Aladin Lite
Author-email: mast-aladin-lite developers <help@stsci.edu>
License: BSD 3-Clause License
Project-URL: Homepage, https://mast-aladin-lite.readthedocs.io/en/latest/
Requires-Python: >=3.10
License-File: LICENSE
Requires-Dist: ipyaladin
Requires-Dist: astroquery
Requires-Dist: sidecar
Provides-Extra: docs
Requires-Dist: sphinx-astropy[confv2]>=1.9.1; extra == "docs"
Requires-Dist: sphinx_design; extra == "docs"
